numerical_function_spaces/__init__.py
numerical_function_spaces/numerical_functions_spaces.py
numerical_function_spaces/orlicz_spaces/__init__.py
numerical_function_spaces/orlicz_spaces/conjugate.py
numerical_function_spaces/orlicz_spaces/norms.py
numerical_function_spaces/orlicz_spaces/orlicz_functions.py
numerical_function_spaces/orlicz_spaces/plots.py
numerical_function_spaces-0.5.0.dist-info/LICENSE
numerical_function_spaces-0.5.0.dist-info/METADATA
numerical_function_spaces-0.5.0.dist-info/WHEEL
numerical_function_spaces-0.5.0.dist-info/RECORD
