Metadata-Version: 2.1
Name: numerical_function_spaces
Version: 0.5.0
Summary: An attempt to numerically study the geometry of the Orlicz function spaces
License: MIT
Author: Adam Bohonos
Requires-Python: >=3.11,<4.0
Classifier: License :: OSI Approved :: MIT License
Classifier: Programming Language :: Python :: 3
Classifier: Programming Language :: Python :: 3.11
Classifier: Programming Language :: Python :: 3.12
Requires-Dist: matplotlib (>=3.9.2,<4.0.0)
Requires-Dist: numpy (>=2.0.1,<3.0.0)
Requires-Dist: tqdm (>=4.66.5,<5.0.0)
